phkit/__init__.py
phkit/chinese/__init__.py
phkit/chinese/convert.py
phkit/chinese/number.py
phkit/chinese/phoneme.py
phkit/chinese/pinyin.py
phkit/chinese/sequence.py
phkit/chinese/style.py
phkit/chinese/symbol.py
phkit/english/__init__.py
phkit/english/cleaners.py
phkit/english/cmu_dict_txt.py
phkit/english/cmudict.py
phkit/english/numbers.py
phkit/english/symbols.py
phkit/pinyinkit/__init__.py
phkit/pinyinkit/core.py
phkit/pinyinkit/phrase_pinyin_txt.py
phkit/pinyinkit/single_pinyin_txt.py
phkit-0.2.11.dist-info/LICENSE
phkit-0.2.11.dist-info/METADATA
phkit-0.2.11.dist-info/WHEEL
phkit-0.2.11.dist-info/top_level.txt
phkit-0.2.11.dist-info/RECORD
