Metadata-Version: 2.1
Name: phkit
Version: 0.2.11
Summary: phoneme toolkit
Home-page: https://github.com/KuangDD/phkit
Author: kuangdd
Author-email: kuangdd@foxmail.com
License: UNKNOWN
Platform: UNKNOWN
Classifier: Intended Audience :: Developers
Classifier: Topic :: Software Development :: Build Tools
Classifier: License :: OSI Approved :: MIT License
Classifier: Programming Language :: Python :: 3.5
Classifier: Programming Language :: Python :: 3.6
Classifier: Programming Language :: Python :: 3.7
Classifier: Operating System :: OS Independent
Requires-Python: >=3.5
Requires-Dist: pypinyin (>=0.41.0)
Requires-Dist: hanziconv
Requires-Dist: jieba (>=0.42.1)
Requires-Dist: tqdm
Requires-Dist: inflect
Requires-Dist: unidecode
